data_insights_pro/__init__.py
data_insights_pro/example.py
data_insights_pro-0.0.1.dist-info/METADATA
data_insights_pro-0.0.1.dist-info/WHEEL
data_insights_pro-0.0.1.dist-info/licenses/LICENSE
data_insights_pro-0.0.1.dist-info/RECORD
