Metadata-Version: 2.3
Name: data_insights_pro
Version: 0.0.1
Summary: Small library with data validation tools
Project-URL: Homepage, https://github.com/4iurchenko
Project-URL: Issues, https://github.com/4iurchenko
Author-email: "Iurii (Yuri) Iurchenko" <4iurchenko@gmail.com>
License-File: LICENSE
Classifier: License :: OSI Approved :: MIT License
Classifier: Operating System :: OS Independent
Classifier: Programming Language :: Python :: 3
Requires-Python: >=3.5
